{
  "lastUpdated": "SomeData",
  "lastUpdatedEpoch": "1643341413234123",
  "sha256": "yfvbhjytrdvbjgfvbnkuh",
  "flights": [
    {
      "dateTime": "Thu 23rd Oct",
      "flightType": "launch" ,
      "flightStatus": "PLANNED" ,
      "earthSite": "ESA The Hague",
      "earthSiteCountryCode": "nl",
      "spaceSite": "Mars",
      "payloadType": "satellite" ,
      "description": "This is an awesome launch This is an awesome launch!",
      "rocketType": "Falcon-5 Heavy",
      "operator": "Space-X"
    }
  ]
}
